envr/__init__.py
envr/envr.py
envr-0.3.6.dist-info/LICENSE
envr-0.3.6.dist-info/METADATA
envr-0.3.6.dist-info/WHEEL
envr-0.3.6.dist-info/top_level.txt
envr-0.3.6.dist-info/RECORD
