Metadata-Version: 2.1
Name: envr
Version: 0.3.6
Summary: Manipulate and transform .env files that are a subset of POSIX-compliant shell scripts.
Home-page: https://github.com/ypcrts/envr
Author: ypcrts
Author-email: ypcrts@users.noreply.github.com
License: MPL 2.0
Keywords: env,dotenv,heroku,environment,python-environ
Platform: UNKNOWN
Classifier: Development Status :: 5 - Production/Stable
Classifier: Programming Language :: Python :: 2.7
Classifier: Programming Language :: Python :: 3
Classifier: Programming Language :: Python :: Implementation :: PyPy
Classifier: Intended Audience :: Developers
Classifier: License :: OSI Approved :: Mozilla Public License 2.0 (MPL 2.0)
Classifier: Intended Audience :: System Administrators
Classifier: Operating System :: OS Independent
Classifier: Topic :: System :: Systems Administration
Classifier: Topic :: Utilities
Classifier: Environment :: Web Environment
Requires-Dist: six
